MatlabRumenjiaochengCYuyanBianchengWangFix1/README.md
MatlabRumenjiaochengCYuyanBianchengWangFix1/__init__.py
MatlabRumenjiaochengCYuyanBianchengWangFix1/__main__.py
MatlabRumenjiaochengCYuyanBianchengWangFix1/file.epub
MatlabRumenjiaochengCYuyanBianchengWangFix1/index.html
MatlabRumenjiaochengCYuyanBianchengWangFix1/css/__init__.py
MatlabRumenjiaochengCYuyanBianchengWangFix1/css/annotations.css
MatlabRumenjiaochengCYuyanBianchengWangFix1/css/main.css
MatlabRumenjiaochengCYuyanBianchengWangFix1/css/normalize.css
MatlabRumenjiaochengCYuyanBianchengWangFix1/css/popup.css
MatlabRumenjiaochengCYuyanBianchengWangFix1/font/__init__.py
MatlabRumenjiaochengCYuyanBianchengWangFix1/font/fontello.eot
MatlabRumenjiaochengCYuyanBianchengWangFix1/font/fontello.svg
MatlabRumenjiaochengCYuyanBianchengWangFix1/font/fontello.ttf
MatlabRumenjiaochengCYuyanBianchengWangFix1/font/fontello.woff
MatlabRumenjiaochengCYuyanBianchengWangFix1/img/__init__.py
MatlabRumenjiaochengCYuyanBianchengWangFix1/img/annotator-glyph-sprite.png
MatlabRumenjiaochengCYuyanBianchengWangFix1/img/annotator-icon-sprite.png
MatlabRumenjiaochengCYuyanBianchengWangFix1/img/apple-touch-icon.png
MatlabRumenjiaochengCYuyanBianchengWangFix1/img/cancelfullscreen.png
MatlabRumenjiaochengCYuyanBianchengWangFix1/img/close.png
MatlabRumenjiaochengCYuyanBianchengWangFix1/img/fullscreen.png
MatlabRumenjiaochengCYuyanBianchengWangFix1/img/loader.gif
MatlabRumenjiaochengCYuyanBianchengWangFix1/img/menu-icon.png
MatlabRumenjiaochengCYuyanBianchengWangFix1/img/save.png
MatlabRumenjiaochengCYuyanBianchengWangFix1/img/saved.png
MatlabRumenjiaochengCYuyanBianchengWangFix1/img/settings-s.png
MatlabRumenjiaochengCYuyanBianchengWangFix1/img/settings.png
MatlabRumenjiaochengCYuyanBianchengWangFix1/img/star.png
MatlabRumenjiaochengCYuyanBianchengWangFix1/js/__init__.py
MatlabRumenjiaochengCYuyanBianchengWangFix1/js/epub.js
MatlabRumenjiaochengCYuyanBianchengWangFix1/js/epub.min.js
matlab_rumenjiaocheng_c_yuyan_biancheng_wang_fix1-2025.3.24.0.dist-info/METADATA
matlab_rumenjiaocheng_c_yuyan_biancheng_wang_fix1-2025.3.24.0.dist-info/WHEEL
matlab_rumenjiaocheng_c_yuyan_biancheng_wang_fix1-2025.3.24.0.dist-info/entry_points.txt
matlab_rumenjiaocheng_c_yuyan_biancheng_wang_fix1-2025.3.24.0.dist-info/top_level.txt
matlab_rumenjiaocheng_c_yuyan_biancheng_wang_fix1-2025.3.24.0.dist-info/RECORD
